MANIFEST.in
README.md
README.txt
requirements.txt
setup.py
trimfilename/__init__.py
trimfilename/main.py
trimfilename/trimfilename.py
trimfilename/utils.py
trimfilename.egg-info/PKG-INFO
trimfilename.egg-info/SOURCES.txt
trimfilename.egg-info/dependency_links.txt
trimfilename.egg-info/entry_points.txt
trimfilename.egg-info/requires.txt
trimfilename.egg-info/top_level.txt