Metadata-Version: 1.0
Name: trimfilename
Version: 0.7.3
Summary: Trim useless characters from filenames
Home-page: https://github.com/tanjot/trimfilename
Author: Tanjot Kaur
Author-email: tanjot28@gmail.com
License: GPLv3
Platform: UNKNOWN
